[
{
    "ROCKER_IMAGE": "geospatial",
    "ROCKER_TAG": "3.6.3-gpu",
    "FROM_IMAGE": "rockerdev/verse:3.6.3-gpu",
    "PARTIAL_DOCKERFILES": "geospatial",
    "UBUNTU_VERSION": "bionic",
    "R_VERSION": "3.6.3"
  },
  {
    "ROCKER_IMAGE": "ml",
    "ROCKER_TAG": "3.6.3-gpu",
    "FROM_IMAGE": "rockerdev/geospatial:3.6.3-gpu",
    "TENSORFLOW_VERSION": "gpu",
    "PARTIAL_DOCKERFILES": "python; tensorflow",
    "UBUNTU_VERSION": "bionic",
    "R_VERSION": "3.6.3"
  },
  {
    "ROCKER_IMAGE": "binder",
    "ROCKER_TAG": "3.6.3-gpu",
    "FROM_IMAGE": "rockerdev/geospatial:3.6.3-gpu",
    "PARTIAL_DOCKERFILES": "python; binder",
    "UBUNTU_VERSION": "bionic",
    "R_VERSION": "3.6.3"
  }

]
